{"_id":"A00686","publicationPlace":"London","title":"A briefe conference betwixt mans frailtie and faith wherein is declared the true vse, and comfort of those blessings pronounced by Christ in the fifth of Matthew, that euery Christian man and woman ought to make and take hold of in their seuerall tentations and conflicts: laide downe in this plaine order of dialogue, to helpe, if it please God, the conceit and feeling of the simplest. By Geruase Babington.","author":"Babington, Gervase, 1550-1610.","publicationDate":"1584","publisher":"Printed by Henry Midleton for Thomas Charde,","notes":["Running title reads: A conference betwixt mans frailtie and faith.","\"Finis\" on p. 132; p. 133 caption title reads: A prayer for a familie in the morning.","Reproduction of the original in the Library of Congress."]}