{"_id":"A01268","publicationPlace":" Monster [i.e. Antwerp","title":"A boke made by Iohn Frith prisoner in the tower of London answeringe vnto M mores lettur which he wrote agenst the first litle treatyse that Iohn̄ Frith made concerninge the sacramente of the body and bloude of, christ vnto which boke are added in the ende the articles of his examinacion before the bishoppes ... for which Iohn Frith was condempned a[n]d after bur[n]et ... the fourth daye of Iuli. Anno. 1533.","author":"Frith, John, 1503-1533.","publicationDate":"1533]","publisher":"Anno 1533 by me Conrade Willems [i.e. H. Peetersen van Middelburch?,","notes":["A reply to: More, Sir Thomas.  Letter of syr Tho. More knyght impugnynge the erronyouse wrytyng of John Fryth agaynst the blessed sacrament of the aultare.","The imprint, from colophon, is false; in fact printed in Antwerp, by H. Peetersen van Middelburch? (STC).","Signatures: A-L.","The last leaf is blank.","Reproduction of the original in the British Library."]}