{"_id":"A01461","titles":["De vera obedientia An oration made in Latine, by the right Reuere[n]de father in God Stepha[n] bishop of Wi[n]chestre, now Lorde Chau[n]celour of Englande. With the preface of Edmonde Bonner ... touching true obedience, printed at Ha[m]burgh in Latine, in officina Fra[n]cisci Rhodi mense Ianuario, 1536. And now translated in to Englishe, and printed eftsones, in Rome, before ye castle of. S. Angel, at the signe of. S. Peter. In nouembre, anno do. M.D.Liij.","De vera obedientia. English"],"author":["Gardiner, Stephen, 1483?-1555.","Bonner, Edmund, 1500?-1569.","Bale, John, 1495-1563.","Wood, Michael, fl. 1553.","Turner, William, d. 1568."],"place":"[Rome [i.e. Wesel? :","date":"1553]","publisher":"Printed by J. Lambrecht? for Hugh Singleton],","notes":["The translation is sometimes attributed to John Bale, to Michael Wood, and to William Turner.","The imprint is false; possibly printed at Wesel by J. Lambrecht; H. Singleton's device appears on H4r (STC).","Signatures: A-G H⁴.","Reproduction of the original in the Henry E. Huntington Library and Art Gallery."],"editionDate":"1553","language":"eng","keywords":["Henry --  VIII, --  King of England, 1491-1547.","Church of England --  Early works to 1800.","Church and state --  Great Britain --  Early works to 1800."]}