{"_id":"A03825","publicationPlace":"Londini","title":"Huloets dictionarie newelye corrected, amended, set in order and enlarged, vvith many names of men, tovvnes, beastes, foules, fishes, trees, shrubbes, herbes, fruites, places, instrumentes &c. And in eche place fit phrases, gathered out of the best Latin authors. Also the Frenche therevnto annexed, by vvhich you may finde the Latin or Frenche, of anye English woorde you will. By Iohn Higgins late student in Oxeforde.","author":"Huloet, Richard.","publicationDate":"Anno 1572.","publisher":"In ædibus Thomæ Marshij,","notes":["An extensively revised edition of: Abcedarium Anglico Latinum.","Signatures: [par.]⁴ A-3A⁶.","Reproduction of the original in the Henry E. Huntington Library and Art Gallery."]}