{"_id":"A06369","titles":["Certaine articles or ordinances made by the French Kinge, and the Duke D'Espernon, to be observed by the French soldyers in the army, for the better goverment [sic] of them","Regulations. 1621?. English"],"author":["France. Armée.","Louis XIII, King of France, 1601-1643."],"place":"At Amsterdam :","date":"anno 1621.","publisher":"Printed by George Veseler,","notes":["Reproduction of the original in the Henry E. Huntington Library and Art Gallery."],"editionDate":"1621","language":"eng"}