{"_id":"A06468","titles":["Bosvvorth-field with a taste of the variety of other poems, left by Sir Iohn Beaumont, Baronet, deceased: set forth by his sonne, Sir Iohn Beaumont, Baronet; and dedicated to the Kings most Excellent Maiestie."],"author":["Beaumont, John, Sir, 1583-1627.","Beaumont, John, Sir, d. 1644."],"place":"London :","date":"1629.","publisher":"Printed by Felix Kyngston for Henry Seile, and are to be sold at the Tygers head in Saint Pauls Churchyard,","notes":["The first leaf is blank.","P. 181-2 are cancelled in all recorded copies.","Reproduction of the original in Cambridge University Library."],"editionDate":"1629","language":"eng","keywords":["Bosworth Field, Battle of, 1485 --  Poetry."]}