{"_id":"A07324","publicationPlace":"London","title":"A continuation of Lucan's historicall poem till the death of Iulius Cæsar by TM","author":"May, Thomas, 1595-1650.","publicationDate":"1630","publisher":"Printed [by J. Haviland] for James Boler at the signe of the Marigold in Pauls Church-yard,","notes":["In verse.","The title page is engraved and signed: T Cockson sculp.","Printer's name from STC.","Signatures: A-K.","The first two leaves and the last leaf are blank.","Reproduction of the original in the Henry E. Huntington Library and Art Gallery."]}