{"_id":"A09188","publicationPlace":"London","title":"An Aprill shower shed in abundance of teares, for the death and incomparable losse, of the right noble, truly religious, and virtuous, Richard Sacuile, Baron of Buckhurst, and Earle of Dorset. VVho departed this life vpon Easter day last, being the 28.th of March, at Dorset-House. By Henry Peacham.","author":"Peacham, Henry, 1576?-1643?","publicationDate":"1624","publisher":"Printed by Edw. Allde,","notes":["In verse.","Running title reads: Vpon the death of the Earle of Dorset.","Reproduction of the original in the Bodleian Library."]}