{"_id":"A09473","publicationPlace":"Cambridge","title":"Tvvo treatises· I. Of the nature and practise of repentance. II. Of the combat of the flesh and spirit.","author":"Perkins, William, 1558-1602.","publicationDate":"1593","publisher":"Printed by Iohn Legate printer to the Vniversitie of Cambridge. 1593. And are to be sold [by Abraham Kitson] at the signe of the Sunne in Paules Church-yard in London,","notes":["By William Perkins.","Bookseller's name from STC.","In this edition, A1r catchword is \"worke,\". Quire [par.] is in the same setting as the other 1593 edition. This is probably the later of the two.","Reproduction of the original in Cambridge University Library."]}