{"_id":"A14719","titles":["Nevves from sea, of tvvo notorious pyrats Ward the Englishman, and Danseker the Dutchman VVith a true relation of all or the most piraces [sic] by them committed vnto the sixt of Aprill. 1609."],"author":["Nixon, Anthony, attributed name."],"place":"Printed at London :","date":"1609.","publisher":"[By Edward Allde] for N. Butter and are to be sold at his shop, at the signe of the pide Bull,","notes":["Sometimes attributed to Anthony Nixon.","Printer's name from STC.","Signatures: A-F⁴.","\"A catalogue of all such shippes, as haue beene taken by .. Captain Ward, and Captain Danseker ..\", F3 (signed B3).","The first leaf bears a woodcut of a ship captioned \"The shippe. that M. Startop of London was taken in\". The last leaf bears a woodcut of a ship captioned \"The charity of M. Megs of London, taken twise\".","Title page cropped, affecting imprint date; lacking A1.","Reproduction of the original in the Henry E. Huntington Library and Art Gallery."],"editionDate":"1609","language":"eng","keywords":["Ward, John, fl. 1603-1615.","Danser, Simon de.","Pirates --  Early works to 1800."]}