{"_id":"A15293","publicationPlace":"London","title":"Triplex, of songes, for three, fower, and fiue voyces ; Medius, of songes, for three, fower, and fiue voyces ; Tenor, of songes, for fiue voyces; Bassus, of songes, for three, fower, and fiue voyces ; [Contratenor for fower [fiue] voyces] composed and made by Thomas Whythorne ...","author":"Whythorne, Thomas, b. 1528.","publicationDate":"1571","publisher":"Printed by John Daye dwelling ouer Aldersgate,","notes":["Contratenor pt. lacking; running title of British Library copy.","\"Now newly published.\"","Title within ornamental border.","Imperfect: item at reel 506:2 lacks all except triplex pt.; item  at 1844:35 lacks contratenor pt. (contratenor pt. from defective British Library copy spliced at end).","Reproduction of original in the Christ Church (University of Oxford). Library."]}