{"_id":"A15589","titles":["A letetr [sic] vvritten by Captaine Edvvard Winne, to the right honourable, Sir George Caluert, Knight, his Maiesties principall secretary: from Feryland in Newfoundland, the 26. of August. 1621"],"author":["Winne, Edward."],"place":"[London :","date":"Imprinted MDCXXI [1621]","publisher":"s.n.],","notes":["Printed by B. Alsop. Cf. STC.","Reproduction of the original in the British Library."],"editionDate":"1621","language":"eng","keywords":["Baltimore, George Calvert, --  Baron 1580-1632 --  Early works to 1800.","Newfoundland --  Description and travel --  Early works to 1800."]}