{"_id":"A15848","title":"The victory of patience and benefit of affliction, with how to husband it so, that the weakest Christian (with blessing from above) may bee able to support himselfe in his most miserable exigents. Together with a counterpoyson or antipoyson against all griefe, being a tenth of the doves innocency, and the serpents subtilty. Extracted out of the choisest authors, ancient and moderne, necessary to be read of all that any way suffer tribulation. By R.Y.","author":"Younge, Richard.","publicationPlace":"London :","publicationDate":"1636.","publisher":"Printed by R. B[adger] and are to be sold [by M. Allot] at the blacke Beare in Pauls Church-yard,"}