{"_id":"A16039","publicationPlace":"Enprynted at Westmynstre","title":"[Desponsacio virginis xpristo. Spousage of a virgin to Christ]","author":"Alcock, John, 1430-1500.","publicationDate":"1497]","publisher":"By Wynkyn de worde,","notes":["Title from STC. Imprint from colophon; publication date conjectured by STC.","On B3r: Here endeth an exhortacyon made to relygyous systers..","Leaf B4 is blank.","Signatures: A⁶ B⁴.","Imperfect; lacks title page (leaf A1).","Reproduction of the original in the Cambridge University Library."]}