{"_id":"A16245","titles":["Irelande Your Maiesties most humble and loyall subiect Baptista Boazio ; grauen by Renolde Elstrack."],"author":["Boazio, Baptista.","Elstracke, Renold, fl. 1590-1630."],"place":"[London] :","date":"[1600?]","publisher":"... are to be sould in the Popes Head Alley, by Mr. Sudbury,","notes":["Date of publication suggested by STC (2nd ed.).","Relief shown pictorially.","Scale from NUC pre-1956 imprints.","Reproduction of original in the British Library."],"editionDate":"1600","language":"eng","keywords":["Ireland --  Maps --  To 1800."]}