{"_id":"A16796","titles":["The copie of a letter vvritten by M. Doctor Allen: concerning the yeelding vp of the citie of Dauentrie vnto his Catholike Maiestie, by Sir VVilliam Stanley knight. VVherin is shevved both hovve lavvful, honorable and necessarie that action vvas; and also that al others, especiallie those of the English nation that detayne anie tovvnes, or other places, in the lovve countries from the King Catholike are bound, vpon paine of damnation, to do the like. Before vvhich is also prefixed a gentlemans letter, that gaue occasion, of this discourse."],"author":["Allen, William, 1532-1594.","R. A., fl. 1587.","Ashton, Roger, d. 1591, attributed name."],"place":"Imprinted at Antuarpe :","date":"Anno 1587.","publisher":"By Ioachim Trognæsius,","notes":["The \"gentlemans letter\" is signed R.A., i.e. Roger Ashton?--STC.","Answered by \"A briefe discouerie of doctor Allens seditious drifts\" (STC 6166).","Running title reads: A letter concerning the rendering of Daventrie.","Imperfect; lacks the \"gentlemans letter\" (A2?).","Reproduction of the original in the British Library."],"editionDate":"1587","language":"eng","keywords":["Stanley, William, --  Sir, 1548-1630 --  Early works to 1800.","Deventer, Surrender of, 1587 --  Early works to 1800."]}