{"_id":"A18322","title":"Iustitia Britannica Per quam liquet perspicue aliquot in eo regno perditos ciues, seditionis & armorum ciuilium authores, regníq[ue] hostium propugnatores acerrimos, vt communi Ecclesiæ reiq[ue] publicæ paci, cautius prospiceretur, morte mulcatatos esse: propter religionem vero, aut cæremonias Romanas, neminem in capitis discrimen vocatum: licet ab aduersarijs secus multò, & admodum malitiosè publicetur. Perscriptum primo in nostrate lingua, deinde versum in Latinam.","author":"Burghley, William Cecil, Baron, 1520-1598.","publicationStmtPlace":"Londini :","publicationStmtDate":"anno M.D.LXXXIIII. [1584] Anno regni Reginæ Elizabethæ XXVI. Mense Martio.","publicationStmtPublisher":"Excudebat Thomas Vautroullerius,","editionDate":"1584"}