{"_id":"A18760","titles":["A pleasaunte laborinth called Churchyardes chance framed on fancies, vttered with verses, and writte[n] to giue solace to euery well disposed mynde: wherein notwithstanding are many heauie epitaphes, sad and sorowfull discourses and sutche a multitude of other honest pastymes for the season (and passages of witte) that the reader therein maie thinke his tyme well bestowed. All whiche workes for the pleasure of the worlde, and recreation of the worthie, are dedicated to the right honourable sir Thomas Bromley knight, lorde Chancelour of Englande.","Churchyardes chance"],"author":["Churchyard, Thomas, 1520?-1604."],"place":"Imprinted at London :","date":"1580.","publisher":"By Ihon Kyngston,","notes":["Dedication signed: Thomas Churchyard.","In verse.","Running title reads: Churchyardes chance.","Reproduction of the original in the Henry E. Huntington Library and Art Gallery."],"editionDate":"1580","language":"eng"}