{"_id":"A19452","publicationPlace":"London","title":"A Pleasant new court song, betweene a young courtier and a countrey lasse to a new court tune.","publicationDate":"ca 1628","publisher":"Printed for Edward Wright,","notes":["Date of publication from STC (2nd ed.).","Contains three woodcut illustrations.","First line: Vpon a summers time,","Printed as a single sheet, bound as two leaves.","Right half of sheet contains: The second part, to the same tune.","Reproduction of original in: Pepys Library."]}