{"_id":"A20920","title":"Certayne letters, translated into English, being first written in Latine. Two, by the reverend and learned Mr. Francis Iunius, divinitie reader at Leyden in Holland. The other, by the exiled English Church, abiding for the present at Amsterdam in Holland. Together with the confession of faith prefixed: where vpon the said letters were first written","author":"Junius, Franciscus, 1545-1602.","publicationPlace":"[Amsterdam] :","publicationDate":"in the yeare. 1602.","publisher":"Printed,"}