{"_id":"A27287","publicationPlace":"London","title":"The Dutch lover a comedy acted at the Dvkes theatre / written by Mrs. A. Bhen [sic]","author":"Behn, Aphra, 1640-1689.","publicationDate":"1673","publisher":"Printed for Thomas Dring ...,","notes":["The plot is founded on a \"pseudo-Spanish novel, entitled 'The history of Don Fenise ... 1651, by Francisco de Las Coveras.'  There is of course no such Spanish author as 'the ingenious Don Francisco de las Coveras.'\"  Cf. Works of A. Behn, ed. by M. Summers, v. 1.","Reproduction of original in Huntington Library."]}