{"_id":"A28206","publicationPlace":"London","title":"The fovr-legg'd elder, or, A horrible relation of a dog and an elders maid to the tune of The lady's fall.","author":"Birkenhead, John, Sir, 1616-1679.","publicationDate":"1647","publisher":"s.n.,","notes":["By John Birkenhead. Cf. Wing.","Imprint from Wing.","Verse - \"All Christians and lay-elders too\".","Annotation on Thomason copy: \"Septemb. 1st\".","Reproductions of the originals in the British Library (reel 246) and in the Harvard University Library (reel 1790)."]}