{"_id":"A28909","publicationPlace":"London","title":"A poem humbly presented to His Most Excellent Majesty King William the Third upon his most miraculuous and happy preservation from that barbarous Jacobitish conspiracy to assassinate His Royal Person, February anno 1695 / by R.B.","author":"Bovet, Richard, b. ca. 1641.","publicationDate":"1696","publisher":"Printed by J. Dover for Richard Baldwin,","notes":["Running title: A poem upon the King's preservation.","Reproduction of original in the Harvard University Library."]}