{"_id":"A29120","titles":["A præsent for Cæsar of 100,000 l. in hand and 50,000 l. a year / by Thomas Bradley ..."],"author":["Bradley, Thomas, 1597-1670."],"place":"London :","date":"[1658]","publisher":"Printed for the author, and are to be sold by Stephen and Thomas Lewis ...,","notes":["Date of publication suggested by Wing.","Reproduction of original in the British Library."],"editionDate":"1658","language":"eng","keywords":["Church of England --  Finance.","Tithes.","Taxation --  England."]}