{"_id":"A29750","titles":["The history of the indulgence shewing its rise, conveyance, progress, and acceptance : together with a demonstration of the unlawfulness thereof and an answere to contrary objections : as also, a vindication of such as scruple to hear the indulged / by a Presbyterian."],"author":["Brown, John, 1610?-1679."],"place":"[Edinburgh? :","date":"1678.","publisher":"s.n.],","notes":["Written by John Brown.  Cf. NUC pre-1956.","Probable place of publication from Wing.","Includes index in manuscript.","Advertisement on p. [1-2] at end.","Reproduction of original in Huntington Library."],"editionDate":"1678","language":"eng","keywords":["Church of Scotland --  History.","Scotland --  History --  1660-1688."]}