{"_id":"A30884","titles":["A letter to a gentleman in the country, giving an account of the two insurance-offices, the Fire-Office & Friendly-Society"],"author":["Barbon, Nicholas, d. 1698."],"place":"London :","date":"1684.","publisher":"Printed by Tho. Milbourn ...,","notes":["Caption title.","Attributed to Nicholas Barbon. Cf. BM.","Imprint from colophon.","Reproduction of original in British Library."],"editionDate":"1684","language":"eng","keywords":["Fire Office (London, England)","Friendly Society (London, England)","Insurance, Fire --  Early works to 1800.","Insurance companies."]}