{"_id":"A34568","titles":["A trve relation of the miseralble [sic] estate that Ireland now standeth in manifested by a letter sent from the Lord Dungarvan, son to the Earle of Corke, to Sir Arthur Magennis, a worthy knight in England : wherein is shewed the great distresse of the Protestants there inhabiting : likwise the preparation for Ireland, by assent of both Houses of Parliament : with the great comfort that they daily receive by meanes of the valour of Sir Simon Harcovrt : with a list of the ships, men, money & ammunition sent for the present reliese of the poore distressed Protestants of Ireland."],"author":["Burlington, Richard Boyle, Earl of, 1612-1698.","Magennis, Arthur, Sir."],"place":"London :","date":"February 9, 1642.","publisher":"Printed by Iohn Hammond,","notes":["Reproduction of original in the Cambridge University Library."],"editionDate":"1642","language":"eng","keywords":["Ireland --  History --  Rebellion of 1641.","Ireland --  History --  1625-1649.","Great Britain --  History --  Charles I, 1625-1649."]}