{"_id":"A36650","titles":["Miscellany poems containing a new translation of Virgills eclogues, Ovid's love elegies, odes of Horace, and other authors : with several original poems / by the most eminent hands."],"author":["Virgil. Bucolica. English.","Dryden, John, 1631-1700.","Dryden, John, 1631-1700. Absalom and Achitophel.","Dryden, John, 1631-1700. Medall.","Dryden, John, 1631-1700. MacFlecknoe."],"place":"London :","date":"1684.","publisher":"Printed for Jacob Tonson ...,","notes":["First in a series of miscellanies published by Tonson, 1684-1709, containing many contributions by Dryden and others. The 5 later volumes were published under various titles.","\"Absalom and Achitophel\" and \"The medall\" each have special t.p. dated 1683. \"Virgil's Eclogues\" has special t.p. and separate paging.","First edition, second issue, with imprint covered by label: London : Printed for Thomas Chapman, 1688.","Advertisements ([2] p.) at end.","Reproduction of original in Huntington Library."],"editionDate":"1684","language":"eng","keywords":["Classical poetry --  Translations into English.","English poetry --  Translations from Greek.","English poetry --  Translations from Latin.","English poetry --  Early modern, 1500-1700."]}