{"_id":"A37525","titles":["The Spanish lady's love to a pleasant new tune, &c."],"author":["Deloney, Thomas, 1543?-1600."],"place":"[London] :","date":"[between 1688 and 1691]","publisher":"Printed by and for W.O. for A.M. and sold by J. Conyers ...,","notes":["Attributed to Thomas Deloney by Wing.","Place and date of imprint suggested by Wing.","\"Licensed and entered according to order.\"","Without music.","Reproduction of original in the Bodleian Library."],"editionDate":"1688","language":"eng","keywords":["Ballads, English."]}