{"_id":"A39864","publicationPlace":"Dublin","title":"A discourse of the plurality of worlds written in French by the most ingenious author of the Dialogues of the dead ; and translated into English by Sir W.D., Knight.","author":"Fontenelle, M. de (Bernard Le Bovier), 1657-1757.","publicationDate":"1687","publisher":"Printed by Andr. Crook and Sam. Helsham, for William Norman ...,","notes":["Translation of: Entretiens sur la pluralité des mondes.","Errata: p. [16].","Reproduction of original in Huntington Library."]}