{"_id":"A41890","titles":["Systema cosmicum autore Galilæo Galilæi ... in quo quatuor dialogis, de duobus maximis mundi systematibus, Ptolemaico & Copernicano, utriusque rationibus philosophicis ac naturalibus indefinitè propositis, differitur ; ex Italica lingua Latine conversum, accessit appendix gemina, qua SS. Scripturæ dicta cum terræ mobilitate conciliantur.","Dialogo dei massimi sistemi. Latin"],"author":["Galilei, Galileo, 1564-1642.","Kepler, Johannes, 1571-1630.","Bernegger, Matthias, 1582-1640.","Foscarini, Paolo Antonio, ca. 1565-1616."],"place":"Londini :","date":"1663.","publisher":"Prostat voenale apud Thomam Dicas ...,","notes":["Translation of: Dialogo dei massimi sistemi.","Title on added engraved t.p.: Dialogus de systemate mundi.","\"Benevole lector\" (translator's preface) signed: Matthias Berneggerus.","Reproduction of original in British Library.","\"Perioche ex introductione in Martem Johannis Kepleri\": p. 650-658.","\"Epistola r.p.m. Pauli Antonii Forscarni Carmlitani, circa Pythagoricorum, & Copernici opinionem de mobilitate terrae et stabilitate solis: et de novo systemate seu constitutione mundi\" (with special t.p.): p. 659-704.","Marginal notes.","Includes index."],"editionDate":"1663","language":"lat","keywords":["Astronomy --  Early works to 1800.","Solar system --  Early works to 1800."]}