{"_id":"A42066","publicationPlace":"Glasgow Scotland","title":"The great and new art of weighing vanity, or, A discovery of the ignorance and arrogance of the great and new artist, in his pseudo-philosophical writings by M. Patrick Mathers, Arch-Bedal to the University of S. Andrews ; to which are annexed some Tentamina de motu penduli & projectorum.","author":"Gregory, James, 1638-1675.","publicationDate":"1672","publisher":"By Robert Sanders ...,","notes":["Usually attributed to Gregory, but sometimes to William Sanders assisted by Gregory.","Satirical attack on George Sinclair & his The hydrostaticks.","Errata: p. [8] at end.","Reproduction of original in Huntington Library."]}