{"_id":"A43269","titles":["A sermon preached before the University of Oxford, December 4, 1687 concerning the obligation of oaths / by Henry Hellier."],"author":["Hellier, Henry, 1662?-1697."],"place":"Oxford :","date":"1688.","publisher":"for Richard Chiswel,","notes":["Reproduction of original in the Union Theological Seminary Library, New York."],"editionDate":"1688","language":"eng","keywords":["Bible. --  O.T. --  Psalms XV, 4 --  Sermons.","Oaths --  Sermons.","Sermons, English --  17th century."]}