{"_id":"A44553","titles":["The Horrid Popish Plot happily discover'd, or, The English Protestants remembrancer a poem on the never-to-be-forgotten powder-treason, and late burning of several cart-loads of popish books at the Royal Exchange."],"place":"London :","date":"1678.","publisher":"Printed for R.G.,","notes":["In verse.","\"Licensed, Nov. 2, 1678.\"","Reproduction of original in the Harvard University Library."],"editionDate":"1678","language":"eng","keywords":["Popish Plot, 1678 --  Poetry.","Great Britain --  Politics and government --  1660-1688 --  Poetry."]}