{"_id":"A44807","titles":["Remarks upon a pamphlet stiled, A letter to a dissenter, &c. in another letter to the same dissenter."],"author":["Halifax, George Savile, Marquis of, 1633-1695."],"place":"[S.l. :","date":"1687]","publisher":"s.n.,","notes":["Reproduction of original in Huntington Library.","Attributed to George Savile Halifax. cf. NUC pre-1956.","Caption title.","Dated: Septemb. 10, 1687."],"editionDate":"1687","language":"eng","keywords":["Halifax, George Savile, --  Marquis of, 1633-1695. --  Letter to a dissenter.","Dissenters, Religious --  Great Britain."]}