{"_id":"A45661","publicationPlace":"London","title":"The defence of the Scots settlement at Darien answer'd paragraph by paragraph / by Philo-Britan.","author":"Harris, Walter, 17th/18th cent.","publicationDate":"1699","publisher":"[s.n.],","notes":["\"Attributed to Walter Harris or Herries\"--Scott, J. Bibl. of ... the Darien company, 1904, p. 22.","Also attributed to Andrew Fletcher of Saltoun and Archibald Foyer. Cf. BM.","Includes the text of the Defence.","Reproduction of original in Yale University Library."]}