{"_id":"A46135","publicationPlace":"Dublin","title":"Whereas divers persons who had passed certificates from His Majesties late commissioners appointed for putting in execution the Acts of Setlement ... by the Lord Lieutenant and Council, J. Roberts.","author":"Ireland. Lord Lieutenant (1669-1670 : Radnor)","publicationDate":"1670","publisher":"Printed by Benjamin Tooke ... and are to be sold by Samuel Dancer ...,","notes":["Title from first 3 lines of text.","Statement of responsibility transposed from head of title.","\"Given at the Council chamber in Dublin, the twentieth eight day of March 1670.\"","Reproduction of original in the Society of Antiquaries Library, London."]}