{"_id":"A50389","title":"A treatise of the gout Written originally in the French tongue, by Theodor Turquet, De Mayerne, knight, Baron of Aubonne, councellor, and chief physitian to the late King and Queen of England. Englished for the general benefit, by Thomas Sherley, M.D. physitian in ordinary to his present Majesty Charles the II. Whereunto is added, advice about hypochondriacal-fits, by the same author.","author":"Mayerne, Théodore Turquet de, Sir, 1573-1655.","publicationPlace":"London :","publicationDate":"1676.","publisher":"printed for D. Newman, at the King's Arms in the Poultrey,"}