{"_id":"A53694","title":"Exercitations concerning the name, original, nature, use, and continuance of a day of sacred rest wherein the original of the Sabbath from the foundation of the world, the morality of the Fourth commandment with the change of the Seventh day are enquired into : together with an assertion of the divine institution of the Lord's Day, and practical directions for its due observation / by John Owen.","author":"Owen, John, 1616-1683.","publicationStmtPlace":"London :","publicationStmtDate":"1671.","publicationStmtPublisher":"Printed by R.W. for Nath. Ponder,","editionDate":"1671"}