{"_id":"A54057","titles":["Some observations, upon that portion of scripture, Romans 14.20 For the service of such in this present age, whose eyes, and hearts the Lord shall please to open to see and consider the weight of the truth thereof. With some few weighty words of advice to several sorts of people, according to their different states. By Isaac Penington."],"author":["Penington, Isaac, 1616-1679."],"place":"London :","date":"1662.","publisher":"printed for Robert Wilson,","notes":["Page 14 contains \"A post-script\".","Reproduction of the original in the Friends House Library, London."],"editionDate":"1662","language":"eng","keywords":["Bible. --  N.T. --  Romans XIV, 20 --  Commentaries --  Early works to 1800."]}