{"_id":"A55203","publicationPlace":"London","title":"The fourth volume of Plutarch's Lives Translated from the Greek, by several hands.","author":"Plutarch.","publicationDate":"MDC.XCIII. 1693","publisher":"printed for Jacob Tonson at the Judges Head in Chancery-lane, near FleetStreet,","notes":["With additional engraved title page, reading: Plutarch's Lives Vol. IIII.","With a final advertisement leaf.","Imperfect: copy catalogued lacks pp.489-496; pp.487-488 are bound after the table in the preliminary leaves.","Reproduction of the original in the British Library."]}