{"_id":"A61588","titles":["A rational account of the grounds of Protestant religion being a vindication of the Lord Archbishop of Canterbury's relation of a conference, &c., from the pretended answer by T.C. : wherein the true grounds of faith are cleared and the false discovered, the Church of England vindicated from the imputation of schism, and the most important particular controversies between us and those of the Church of Rome throughly examined / by Edward Stillingfleet ..."],"author":["Stillingfleet, Edward, 1635-1699."],"place":"London :","date":"1665.","publisher":"Printed by Rob. White for Henry Mortlock ...,","notes":["An answer to Thomas Carwell's Labyrinthus Cantuariensis.","Conference is between Laud and Fisher.  Cf. BM.","Reproduction of original in Huntington Library."],"editionDate":"1665","language":"eng","keywords":["Laud, William, 1573-1645. --  Relation of the conference between William Laud, late Lord Archbishop of Canterbury, and Mr. Fisher the Jesuit.","Carwell, Thomas, 1600-1664. --  Labyrinthus Cantuariensis.","Church of England --  Doctrines.","Catholic Church --  Controversial literature.","Protestantism --  Apologetic works."]}