{"_id":"A63218","titles":["The Tryals of Peter Boss, George Keith, Thomas Budd, and William Bradford, Quakers for several great misdemeanors (as was pretended by their adversaries) before a court of Quakers at the sessions held at Philadelphia in Pensylvania, the ninth, tenth, and twelfth days of December, 1692 : giving also an account of the most arbitrary procedure of that court."],"author":["Keith, George, 1639?-1716.","Boss, Peter."],"place":"London :","date":"1693.","publisher":"Reprinted for Richard Baldwin,","notes":["Attributed to George Keith--LC.","Reproduction of original in the Bodleian Library."],"editionDate":"1693","language":"eng","keywords":["Society of Friends --  Controversial literature.","Society of Friends --  Pennsylvania."]}