{"_id":"A66783","titles":["Three grains of spirituall frankincense infused into three hymnes of praise, and humbly offered toward the publike thanksgiving, commanded by authority of Parliament to be celebrated throughout the Commonwealth of England, the 30 of this present January, 1650."],"author":["Wither, George, 1588-1667."],"place":"London :","date":"1651.","publisher":"Printed by R. Austin,","notes":["Reproduction of original in Huntington Library.","Attributed to George Wither. cf. NUC pre-1956.","In verse."],"editionDate":"1651","language":"eng","keywords":["Great Britain --  History --  Puritan Revolution, 1642-1660 --  Poetry."]}