{"_id":"A67232","titles":["An assize-sermon preached in the cathedral-church of St. Peter in York, March the 8th, 1685/6, before the Right Honourable Sir Edward Nevill and Sir Henry Bedingfield ... by Christopher Wyvill ..."],"author":["Wyvill, Christopher, 1651?-1711."],"place":"London :","date":"1686.","publisher":"Printed for Walter Kettilby ...,","notes":["Reproduction of original in Huntington Library."],"editionDate":"1686","language":"eng","keywords":["Bible. --  O.T. --  Judges XVII, 6 --  Sermons.","Sermons, English --  17th century."]}