{"_id":"A83790","publicationPlace":"London","title":"Die Sabbati 30⁰. Decemb. 1643. Ordered that the adventurers of this house for lands in Ireland, and the body of adventurers in London, doe meete at Grocers-Hall on Thursday in the afternoone at two of the clock, and take into their serious consideration by what wayes and meanes the British Army in Vlster, opposing the cessation may be maintained and encouraged to proceed in prosecution of that warre of Ireland against the Rebels, and to prepare some propositions to be presented to the House. And the ministers of the severall churches and chappels in and about London, are to signifie this order in their severall churches, that all may take speciall notice thereof. Hen. Elsyng, Cler. Parl. D. Com.","publicationDate":"1643","publisher":"s.n.,","notes":["Place of publication from Wing.","Reproduction of the original in the British Library."]}