{"_id":"A84145","publicationPlace":"Printed at London","title":"An elegie and epitapth [sic], upon the Right Honourable the Lord Francis Villars: written by an affectionate servant to his family, kinsman to his person, and prisoner for the same caus this noble lord so bravely dyed in.","publicationDate":"1648","publisher":"[s.n.],","notes":["Verse - \"What are the crying sins of this our State,\".","Woodcut mememto mori at head of verse.","Annotation on Thomason copy: \"Aug. 4th.\".","Reproduction of the original in the British Library."]}