{"_id":"A85011","titles":["Three proclamations by His Excellency the Lord General Fairfax; the first commanding the civil deportment of the souldiery. The second that no souldier shall depart from his quarters without leave. The third that all ill-affected persons, that have engaged for the King, in the first or latter war, and are now residing in or about London, shall depart the said city, and suburbs, and all places ten miles distant from thence, within twenty four hours next after publication hereof."],"author":["Fairfax, Thomas Fairfax, Baron, 1612-1671."],"place":"London :","date":"1648.","publisher":"Printed for John Partridge, and George Whittington,","notes":["Annotation on Thomason copy: \"Decemb: 5\".","Reproduction of the original in the British Library."],"editionDate":"1648","language":"eng","keywords":["Royalists --  England --  History --  17th century --  Early works to 1800.","Great Britain --  History --  Civil War, 1642-1649 --  Collaborationists --  Early works to 1800."]}