{"_id":"A92692","titles":["A proclamation for discovering who robbed the packquit","Proclamations. 1692-08-15"],"author":["Scotland. Privy Council."],"place":"[Edinburgh :","date":"1692]","publisher":"printed by the heir of Andrew Anderson,","notes":["Imprint from Wing (CD-ROM edition).","At end of text: Given under our signet at Edinburgh, the fifteenth day of August, and of our reign the fourth year, 1692.","Steele notation: Arms 245  Defen- Contempt be.","Copy filmed at UMI microfilm Early English Books 1641-1700 reel 2359 cropped; lacking imprint.","Reproduction of original in the Folger Shakespeare Library."],"editionDate":"1692","language":"eng","keywords":["Brigands and robbers --  Scotland --  Early works to 1800.","Broadsides --  Scotland"]}