{"_id":"A92812","publicationPlace":"London","title":"The second humble addresse of those who are called Anabaptists in the county of Lincoln Presented to His Majesty, Charles the Second, King of England, Scotland, France, and Ireland, &c.","author":"Grantham, Thomas, 1634-1692.","publicationDate":"1660 i.e. 1661","publisher":"Printed by Simon Dover, in Martins near Aldersgate,","notes":["Actual publication date from Wing.","Praying for the redress of their grievances.","The first 'e' on the title page is printed backwards.","Signed by Thomas Grentham (i.e. Grantham) and 29 others.","Annotation on Thomason copy: \"Feb: 6.\"","Reproduction of the original in the British Library."]}