{"_id":"B05127","titles":["The religious mans exhortation to all persons of what degree soever, especially youth; that they may fear God and honour their parents. Reform thy life then free from strife, thou wouldst be perfect free, when e're you dye, assuredly, to true felicity. To the tune of, The young-man's legacy: or, Sinners redemption."],"place":"[London] :","date":"[between 1685-1688]","publisher":"Printed for P. Brooksby, at the Golden-Ball in Pye-Corner,","notes":["Date and place of publication suggested by Wing.","Verse: \"Both young and old I pray attend ...\"","Item at A5:2[314] imperfect: trimmed, affecting imprint.","Reproduction of original in the Harvard University, Houghton Library and the British Library."],"editionDate":"1685-1688?","language":"eng","keywords":["Ballads, English --  17th century."]}